{
  "metadados": {
    "jogo_numero": "13",
    "concurso_numero": "atual"
  },
  "dados": {
    "numero": "jogo_13",
    "time_casa": "BRAGANTINO/SP",
    "time_fora": "ATLETICO/MG",
    "arena": "Bragança/PS",
    "campeonato": "Brasileirão Série A",
    "dia": "Domingo",
    "escudo_casa": "\\static\\escudos\\RBB_Bragantino\\RedBull_Bragantino.png",
    "escudo_fora": "\\static\\escudos\\CAM_Atletico-MG\\Atletico_MG.png",
    "probabilidade_casa": "25",
    "probabilidade_empate": "35",
    "probabilidade_fora": "40",
    "recomendacao": "Recomendação Estatística: TRIPLO - Risco Alto",
    "conclusao_analista": "Olhando para todos os dados, este confronto entre Red Bull Bragantino e Atlético-MG tem um histórico que não mente: o Atlético domina. Em termos de momento, o Atlético-MG chega melhor: invicto nos últimos três jogos, com duas vitórias e um empate, enquanto o Bragantino oscila mais – mesmo em casa, apesar da importante vitória contra o São Paulo. \nEstatisticamente, o Bragantino tem médias defensivas preocupantes: sofre 1,56 gols por jogo, e em 63% dos seus jogos ambos os times marcam. Já o Atlético é mais equilibrado, sofre menos (1,06) e tem 38% dos jogos sem tomar gol.",
    "confrontos_sequence": "(03/08/2025, 2-1, ATLETICO|\\static\\escudos\\CAM_Atletico-MG\\Atletico_MG.png) (22/09/2024, 3-0, ATLETICO|\\static\\escudos\\CAM_Atletico-MG\\Atletico_MG.png) (11/06/2024, 1-2, ATLETICO|\\static\\escudos\\CAM_Atletico-MG\\Atletico_MG.png) (25/10/2023, 1-2, ATLETICO|\\static\\escudos\\CAM_Atletico-MG\\Atletico_MG.png) (10/06/2023, 1-1, Empate|/static/escudos/Empate.png) (07/09/2022, 1-1, Empate|/static/escudos/Empate.png) (11/05/2022, 1-1, Empate|/static/escudos/Empate.png) (05/12/2021, 4-3, ATLETICO|\\static\\escudos\\CAM_Atletico-MG\\Atletico_MG.png) (29/08/2021, 1-1, Empate|/static/escudos/Empate.png) (11/01/2021, 2-2, Empate|/static/escudos/Empate.png)",
    "posicao_casa": "11",
    "posicao_fora": "9",
    "confronto_direto": "0V-5E-5D",
    "fator_casa": "45",
    "fator_fora": "55",
    "analise_posicao": "Vantagem Atletico-MG",
    "analise_posicao_tabelas": "Confronto Equilibrado",
    "analise_confronto_direto": "Vantagem Atletico-MG",
    "analise_fator_casa": "Confronto Equilibrado",
    "arquivo_confrontos": "Atletico-MG_vs_RBB_Bragantino.csv",
    "sincronizado_em": "2025-11-12T12:43:41.523Z"
  }
}